related/__init__.py
related/_init_fields.py
related/converters.py
related/decorators.py
related/dispatchers.py
related/fields.py
related/functions.py
related/types.py
related/validators.py
related_2-0.7.3.dist-info/LICENSE
related_2-0.7.3.dist-info/METADATA
related_2-0.7.3.dist-info/WHEEL
related_2-0.7.3.dist-info/top_level.txt
related_2-0.7.3.dist-info/RECORD
