Metadata-Version: 2.1
Name: related-2
Version: 0.7.3
Summary: Related: Straightforward nested object models in Python
Home-page: https://github.com/M0r13n/related
License: MIT license
Keywords: related object models yaml json dict nested
Platform: UNKNOWN
Classifier: Intended Audience :: Developers
Classifier: License :: OSI Approved :: MIT License
Classifier: Natural Language :: English
Classifier: Programming Language :: Python :: 3
Classifier: Programming Language :: Python :: 3.6
Classifier: Programming Language :: Python :: 3.7
Requires-Dist: PyYAML
Requires-Dist: attrs (>=19.3.0)
Requires-Dist: future
Requires-Dist: python-dateutil
Requires-Dist: singledispatch ; python_version < "3.4"
